ninebit_ciq/__init__.py
ninebit_ciq/app_types.py
ninebit_ciq/cli.py
ninebit_ciq/client.py
ninebit_ciq/logger.py
ninebit_ciq/remote_utils.py
ninebit_ciq/sharepoint.py
ninebit_ciq-1.1.1.dist-info/licenses/LICENSE
ninebit_ciq-1.1.1.dist-info/METADATA
ninebit_ciq-1.1.1.dist-info/WHEEL
ninebit_ciq-1.1.1.dist-info/top_level.txt
ninebit_ciq-1.1.1.dist-info/RECORD
