Metadata-Version: 2.4
Name: ninebit-ciq
Version: 1.1.1
Summary: Thin client for interacting with NineBit CIQ backend
Home-page: https://ciq.ninebit.in
Author: NineBit Computing Pvt Ltd
Author-email: rajeev.jamaiyar@ninebit.in
Project-URL: Source, https://github.com/NineBit-Computing/ciq-py-client
Project-URL: Tracker, https://github.com/NineBit-Computing/ciq-py-client/issues
Classifier: Programming Language :: Python :: 3
Classifier: Operating System :: OS Independent
Classifier: License :: OSI Approved :: MIT License
Requires-Python: >=3.11
License-File: LICENSE
Requires-Dist: requests>=2.31.0
Requires-Dist: msal>=1.32.3
Requires-Dist: python-dotenv>=1.1.1
Dynamic: license-file
